main.py
src/__init__.py
src/calc.py
src/core.py
src/functions.py
src/knowledge_base.json
Hoobler-0.1.0.dist-info/METADATA
Hoobler-0.1.0.dist-info/WHEEL
Hoobler-0.1.0.dist-info/entry_points.txt
Hoobler-0.1.0.dist-info/top_level.txt
Hoobler-0.1.0.dist-info/RECORD
