Metadata-Version: 2.1
Name: Hoobler
Version: 0.1.0
Summary: Assistente I.A. com foco em ser uma central de atalhos.
Home-page: https://github.com/vegedra/hoobler
Author: Pedro Ivo
Author-email: pedro0513@gmail.com
Classifier: Programming Language :: Python :: 3
Classifier: License :: OSI Approved :: MIT License
Classifier: Operating System :: OS Independent
Requires-Python: >=3.6
Requires-Dist: curses ; platform_system != "Windows"
Requires-Dist: windows-curses ; platform_system == "Windows"
